fnirs_toolkit/README.md
fnirs_toolkit/__init__.py
fnirs_toolkit/flowchart.png
fnirs_toolkit/data/channel_region_map.json
fnirs_toolkit/data/HB/HB_sample01.csv
fnirs_toolkit/data/raw/raw_sample01.csv
fnirs_toolkit/examples/advanced_analysis.py
fnirs_toolkit/examples/basic_pipeline.py
fnirs_toolkit/nirs_analysis/__init__.py
fnirs_toolkit/nirs_analysis/connectivity.py
fnirs_toolkit/nirs_analysis/glm.py
fnirs_toolkit/nirs_analysis/integration.py
fnirs_toolkit/nirs_analysis/statistics.py
fnirs_toolkit/nirs_analysis/__pycache__/__init__.cpython-311.pyc
fnirs_toolkit/nirs_analysis/__pycache__/integration.cpython-311.pyc
fnirs_toolkit/nirs_io/Cope_ext_coeff_table.txt
fnirs_toolkit/nirs_io/__init__.py
fnirs_toolkit/nirs_io/converters.py
fnirs_toolkit/nirs_io/hb_io.py
fnirs_toolkit/nirs_io/od_io.py
fnirs_toolkit/nirs_io/raw_io.py
fnirs_toolkit/nirs_io/__pycache__/__init__.cpython-311.pyc
fnirs_toolkit/nirs_io/__pycache__/converters.cpython-311.pyc
fnirs_toolkit/nirs_io/__pycache__/hb_io.cpython-311.pyc
fnirs_toolkit/nirs_io/__pycache__/od_io.cpython-311.pyc
fnirs_toolkit/nirs_io/__pycache__/raw_io.cpython-311.pyc
fnirs_toolkit/nirs_plot/__init__.py
fnirs_toolkit/nirs_plot/channel_location_ZLHK_Plate.csv
fnirs_toolkit/nirs_plot/channel_plot.py
fnirs_toolkit/nirs_plot/hb_plot.py
fnirs_toolkit/nirs_plot/od_plot.py
fnirs_toolkit/nirs_plot/quality_plot.py
fnirs_toolkit/nirs_plot/region_plot.py
fnirs_toolkit/nirs_plot/__pycache__/__init__.cpython-311.pyc
fnirs_toolkit/nirs_plot/__pycache__/hb_plot.cpython-311.pyc
fnirs_toolkit/nirs_plot/__pycache__/od_plot.cpython-311.pyc
fnirs_toolkit/nirs_preprocess/__init__.py
fnirs_toolkit/nirs_preprocess/epoching.py
fnirs_toolkit/nirs_preprocess/filter.py
fnirs_toolkit/nirs_preprocess/hb_preprocess.py
fnirs_toolkit/nirs_preprocess/od_quality.py
fnirs_toolkit/nirs_preprocess/preprocess_helper.py
fnirs_toolkit/nirs_preprocess/raw_quality.py
fnirs_toolkit/nirs_preprocess/resample.py
fnirs_toolkit/nirs_preprocess/tddr.py
fnirs_toolkit-0.3.9.dist-info/METADATA
fnirs_toolkit-0.3.9.dist-info/WHEEL
fnirs_toolkit-0.3.9.dist-info/entry_points.txt
fnirs_toolkit-0.3.9.dist-info/top_level.txt
fnirs_toolkit-0.3.9.dist-info/RECORD
