Metadata-Version: 2.4
Name: fnirs-toolkit
Version: 0.3.9
Summary: A comprehensive Python package for fNIRS data analysis
Home-page: https://github.com/xzywisdili/fNIRSAnalysisProcess
Author: Jamie, Wendy
Author-email: Your Team <your.email@example.com>
Maintainer-email: Your Team <your.email@example.com>
License: MIT
Project-URL: Homepage, https://github.com/yourusername/fnirs-toolkit
Project-URL: Documentation, https://fnirs-toolkit.readthedocs.io/
Project-URL: Repository, https://github.com/yourusername/fnirs-toolkit.git
Project-URL: Bug Tracker, https://github.com/yourusername/fnirs-toolkit/issues
Keywords: fnirs,neuroimaging,signal processing,hemodynamics,brain imaging
Classifier: Development Status :: 3 - Alpha
Classifier: Intended Audience :: Science/Research
Classifier: Topic :: Scientific/Engineering :: Medical Science Apps.
Classifier: License :: OSI Approved :: MIT License
Classifier: Programming Language :: Python :: 3
Classifier: Programming Language :: Python :: 3.8
Classifier: Programming Language :: Python :: 3.9
Classifier: Programming Language :: Python :: 3.10
Classifier: Programming Language :: Python :: 3.11
Requires-Python: >=3.8
Requires-Dist: numpy>=1.20.0
Requires-Dist: pandas>=1.3.0
Requires-Dist: scipy>=1.7.0
Requires-Dist: scikit-learn>=1.0.0
Requires-Dist: matplotlib>=3.4.0
Requires-Dist: seaborn>=0.11.0
Requires-Dist: statsmodels>=0.12.0
Requires-Dist: h5py>=3.1.0
Requires-Dist: openpyxl>=3.0.0
Requires-Dist: tqdm>=4.60.0
Requires-Dist: pyyaml>=5.4.0
Requires-Dist: joblib>=1.0.0
Provides-Extra: dev
Requires-Dist: pytest>=6.0; extra == "dev"
Requires-Dist: pytest-cov>=2.0; extra == "dev"
Requires-Dist: black>=21.0; extra == "dev"
Requires-Dist: flake8>=3.8; extra == "dev"
Requires-Dist: mypy>=0.910; extra == "dev"
Requires-Dist: pre-commit>=2.15.0; extra == "dev"
Provides-Extra: docs
Requires-Dist: sphinx>=4.0; extra == "docs"
Requires-Dist: sphinx-rtd-theme>=1.0; extra == "docs"
Requires-Dist: myst-parser>=0.15; extra == "docs"
Requires-Dist: sphinx-autodoc-typehints>=1.12; extra == "docs"
Provides-Extra: advanced
Requires-Dist: mne>=1.0.0; extra == "advanced"
Requires-Dist: plotly>=5.0.0; extra == "advanced"
Requires-Dist: dash>=2.0.0; extra == "advanced"
Dynamic: author
Dynamic: home-page
Dynamic: requires-python
